memosa/__init__.py
memosa/context.py
memosa/json.py
memosa-0.5.0.dist-info/LICENSE
memosa-0.5.0.dist-info/METADATA
memosa-0.5.0.dist-info/WHEEL
memosa-0.5.0.dist-info/top_level.txt
memosa-0.5.0.dist-info/RECORD
